<?xml version="1.0" encoding="UTF-8" standalone="yes"?>
<node xmlns="urn:enonic:xp:export:1.0">
    <childOrder>_modifiedtime DESC</childOrder>
    <nodeType>content</nodeType>
    <properties>
        <boolean name="draft">false</boolean>
        <string name="displayName">BobaFettEAtlas.jpg</string>
        <string name="type">system:image</string>
        <property-set name="data">
            <string name="media">BobaFettEAtlas.jpg</string>
            <string name="mimeType">image/jpeg</string>
            <property-set name="metadata">
                <string name="date">2009-09-06T13:03:04</string>
                <string name="printFlagsInformation">0 1 0 0 0 0 0 0 0 2</string>
                <string name="slices">Untitled-3 (0,0,900,656) 1 Slices</string>
                <string name="compressionType">Baseline</string>
                <string name="thumbnailCompression">JPEG (old-style)</string>
                <string name="printFlags">0 0 0 0 0 0 0 0 1</string>
                <string name="numberOfComponents">3</string>
                <string name="component2">Cb component: Quantization table 1, Sampling factors 1 horiz/1 vert</string>
                <string name="component1">Y component: Quantization table 0, Sampling factors 1 horiz/1 vert</string>
                <string name="tiffResolutionunit">Inch</string>
                <string name="seedNumber">1</string>
                <string name="XResolution">72 dots per inch</string>
                <string name="versionInfo">1 (Adobe Photoshop, Adobe Photoshop CS3) 1</string>
                <string name="component3">Cr component: Quantization table 1, Sampling factors 1 horiz/1 vert</string>
                <string name="modified">2009-09-06T13:03:04</string>
                <string name="thumbnailData">JpegRGB, 117x160, Decomp 56320 bytes, 1572865 bpp, 7914 bytes</string>
                <string name="tiffBitspersample">8</string>
                <string name="resolutionInfo">600.0x600.0 DPI</string>
                <string name="metaCreationDate">2009-09-06T13:03:04</string>
                <string name="captionDigest">[16 bytes]</string>
                <string name="creationDate">2009-09-06T13:03:04</string>
                <string name="orientation">Top, left side (Horizontal / normal)</string>
                <string name="tiffOrientation">1</string>
                <string name="tiffSoftware">Adobe Photoshop CS3 Windows</string>
                <string name="thumbnailOffset">302 bytes</string>
                <string name="globalAngle">120</string>
                <string name="exifImageHeight">900 pixels</string>
                <string name="software">Adobe Photoshop CS3 Windows</string>
                <string name="copyrightFlag">No</string>
                <string name="tiffYresolution">600.0</string>
                <string name="YResolution">72 dots per inch</string>
                <string name="colorTransferFunctions">[112 bytes]</string>
                <string name="dataPrecision">8 bits</string>
                <string name="tiffImagelength">900</string>
                <string name="jpegQuality">12 (Maximum), Standard format, 3 scans</string>
                <string name="dctermsCreated">2009-09-06T13:03:04</string>
                <string name="dctermsModified">2009-09-06T13:03:04</string>
                <string name="lastModified">2009-09-06T13:03:04</string>
                <string name="lastSaveDate">2009-09-06T13:03:04</string>
                <string name="thumbnailLength">7914 bytes</string>
                <string name="colorSpace">sRGB</string>
                <string name="globalAltitude">30</string>
                <string name="metaSaveDate">2009-09-06T13:03:04</string>
                <string name="contentType">image/jpeg</string>
                <string name="XParsedBy">Proxy5edc9051_6af9_4c56_be4a_6a0a487229d4</string>
                <string name="resolutionUnits">inch</string>
                <string name="colorHalftoningInformation">[72 bytes]</string>
                <string name="tiffXresolution">600.0</string>
                <string name="dateTime">2009:09:06 13:03:04</string>
                <string name="gridAndGuidesInformation">[16 bytes]</string>
                <string name="exifImageWidth">656 pixels</string>
                <string name="imageHeight">900 pixels</string>
                <string name="pixelAspectRatio">1.0</string>
                <string name="imageWidth">656 pixels</string>
                <string name="resolutionUnit">Inch</string>
                <string name="urlList">0</string>
                <string name="printScale">Centered, Scale 1.0</string>
                <string name="tiffImagewidth">656</string>
                <string name="printInfo">[74 bytes]</string>
            </property-set>
        </property-set>
        <property-set name="attachment">
            <string name="name">BobaFettEAtlas.jpg</string>
            <string name="label">source</string>
            <binaryReference name="binary">BobaFettEAtlas.jpg</binaryReference>
            <string name="mimeType">image/jpeg</string>
            <long name="size">892224</long>
        </property-set>
        <property-set name="attachment">
            <string name="name">BobaFettEAtlas_small.jpg</string>
            <string name="label">small</string>
            <binaryReference name="binary">BobaFettEAtlas_small.jpg</binaryReference>
            <string name="mimeType">image/jpeg</string>
            <long name="size">20487</long>
        </property-set>
        <property-set name="attachment">
            <string name="name">BobaFettEAtlas_medium.jpg</string>
            <string name="label">medium</string>
            <binaryReference name="binary">BobaFettEAtlas_medium.jpg</binaryReference>
            <string name="mimeType">image/jpeg</string>
            <long name="size">67594</long>
        </property-set>
    </properties>
    <attachedBinaries>
        <attachedBinary>
            <binaryReference>BobaFettEAtlas.jpg</binaryReference>
        </attachedBinary>
        <attachedBinary>
            <binaryReference>BobaFettEAtlas_small.jpg</binaryReference>
        </attachedBinary>
        <attachedBinary>
            <binaryReference>BobaFettEAtlas_medium.jpg</binaryReference>
        </attachedBinary>
    </attachedBinaries>
    <indexConfigs>
        <analyzer>content_default</analyzer>
        <defaultConfig>
            <decideByType>true</decideByType>
            <enabled>true</enabled>
            <nGram>false</nGram>
            <fulltext>false</fulltext>
            <includeInAllText>false</includeInAllText>
        </defaultConfig>
        <pathIndexConfigs>
            <pathIndexConfig>
                <indexConfig>
                    <decideByType>false</decideByType>
                    <enabled>false</enabled>
                    <nGram>false</nGram>
                    <fulltext>false</fulltext>
                    <includeInAllText>false</includeInAllText>
                </indexConfig>
                <path>draft</path>
            </pathIndexConfig>
            <pathIndexConfig>
                <indexConfig>
                    <decideByType>true</decideByType>
                    <enabled>true</enabled>
                    <nGram>false</nGram>
                    <fulltext>false</fulltext>
                    <includeInAllText>false</includeInAllText>
                </indexConfig>
                <path>data</path>
            </pathIndexConfig>
            <pathIndexConfig>
                <indexConfig>
                    <decideByType>false</decideByType>
                    <enabled>false</enabled>
                    <nGram>false</nGram>
                    <fulltext>false</fulltext>
                    <includeInAllText>false</includeInAllText>
                </indexConfig>
                <path>page</path>
            </pathIndexConfig>
            <pathIndexConfig>
                <indexConfig>
                    <decideByType>false</decideByType>
                    <enabled>false</enabled>
                    <nGram>false</nGram>
                    <fulltext>false</fulltext>
                    <includeInAllText>false</includeInAllText>
                </indexConfig>
                <path>site</path>
            </pathIndexConfig>
            <pathIndexConfig>
                <indexConfig>
                    <decideByType>false</decideByType>
                    <enabled>true</enabled>
                    <nGram>false</nGram>
                    <fulltext>false</fulltext>
                    <includeInAllText>false</includeInAllText>
                </indexConfig>
                <path>type</path>
            </pathIndexConfig>
        </pathIndexConfigs>
    </indexConfigs>
</node>
